{"skeleton":{"hash":"J0NEWCP6kQYQQjRNUHCz0RSSBqA","spine":"3.8.00","x":0,"y":0,"width":186.77,"height":371.46,"images":"./","audio":""},"bones":[{"name":"root"},{"name":"ALL","parent":"root","x":22.77,"y":165.31},{"name":"canying_jienuosi4XT","parent":"root","x":-260.47,"y":131.16},{"name":"global/yinying","parent":"root","x":1.99,"y":-1.03,"scaleX":0.439,"scaleY":0.478},{"name":"a_kua","parent":"ALL","x":0.42,"y":-1.46,"rotation":-90.45,"length":14.25},{"name":"a_shenti","parent":"ALL","x":-0.63,"y":3.53,"rotation":90.0,"length":45.04},{"name":"a_youdatui","parent":"ALL","x":-12.06,"y":-5.62,"rotation":-107.07,"length":55.66},{"name":"a_zuodatui","parent":"ALL","x":7.07,"y":-9.45,"rotation":-83.26,"length":54.17},{"name":"a_youxiaotui","parent":"a_youdatui","x":55.35,"y":-0.43,"rotation":5.39,"length":54.53},{"name":"a_zuoxioatui","parent":"a_zuodatui","x":54.21,"y":0.68,"rotation":-59.1,"length":51.08},{"name":"bone","parent":"a_shenti","x":45.04,"rotation":8.94,"length":42.59},{"name":"a_cheek","parent":"bone","x":42.27,"rotation":-8.06,"length":34.11},{"name":"a_youjiao","parent":"a_youxiaotui","x":55.35,"y":-0.66,"rotation":-87.95,"length":33.62,"transform":"noRotationOrReflection"},{"name":"a_zuojiao","parent":"a_zuoxioatui","x":48.38,"y":-0.14,"rotation":-87.29,"length":32.35,"transform":"noRotationOrReflection"},{"name":"bone2","parent":"bone","x":25.71,"y":-9.66,"rotation":-85.49,"length":20.19},{"name":"bone3","parent":"bone","x":28.89,"y":8.19,"rotation":75.43,"length":25.66},{"name":"bone48","parent":"bone","x":35.94,"y":46.81,"rotation":137.88,"length":43.5},{"name":"bone49","parent":"bone","x":26.18,"y":-25.01,"rotation":137.88,"length":43.5},{"name":"a_youdabi","parent":"bone3","x":36.05,"y":-5.67,"rotation":78.86,"length":48.69},{"name":"a_youtuijin","parent":"bone3","x":44.05,"y":-3.35},{"name":"a_zuodabi","parent":"bone2","x":20.73,"y":-0.77,"rotation":-94.5,"length":48.3},{"name":"a_zuotuijin","parent":"bone2","x":18.49,"y":4.7},{"name":"bone29","parent":"a_cheek","x":56.66,"y":9.27,"rotation":150.79,"length":15.84},{"name":"bone32","parent":"a_cheek","x":55.87,"y":-6.62,"rotation":-174.15,"length":9.11},{"name":"bone35","parent":"a_cheek","x":55.49,"y":-17.08,"rotation":-171.86,"length":10.05},{"name":"bone38","parent":"a_cheek","x":58.31,"y":-24.97,"rotation":-152.53,"length":13.65},{"name":"bone41","parent":"a_cheek","x":56.83,"y":-22.35,"rotation":-123.48,"length":12.32},{"name":"bone44","parent":"a_cheek","x":58.39,"y":22.66,"rotation":166.28,"length":16.59},{"name":"bone5","parent":"a_cheek","x":71.73,"y":17.07},{"name":"guangqiu_jienuosi4XT5","parent":"bone48","x":-4.27,"y":-11.26,"rotation":-77.56,"scaleX":1.238,"scaleY":0.581,"length":24.56},{"name":"guangqiu_jienuosi4XT6","parent":"bone48","x":-4.27,"y":-11.26,"rotation":-77.56,"scaleX":1.238,"scaleY":0.581,"length":24.56},{"name":"texiao_4_jienuosi4XT","parent":"bone48","x":-2.52,"y":-4.12,"rotation":123.16},{"name":"texiao_4_jienuosi4XT2","parent":"bone48","x":-2.52,"y":-4.12,"rotation":123.16},{"name":"texiao_4_jienuosi4XT3","parent":"bone48","x":-2.52,"y":-4.12,"rotation":123.16},{"name":"texiao_4_jienuosi4XT4","parent":"bone48","x":-2.52,"y":-4.12,"rotation":123.16},{"name":"texiao_4_jienuosi4XT5","parent":"bone49","x":-2.52,"y":-4.12,"rotation":123.16},{"name":"texiao_4_jienuosi4XT6","parent":"bone49","x":-2.52,"y":-4.12,"rotation":123.16},{"name":"texiao_4_jienuosi4XT7","parent":"bone49","x":-2.52,"y":-4.12,"rotation":123.16},{"name":"texiao_4_jienuosi4XT8","parent":"bone49","x":-2.52,"y":-4.12,"rotation":123.16},{"name":"a_youtuijin22","parent":"a_youtuijin","x":3.77,"y":-0.5,"rotation":-49.1,"length":25.95},{"name":"a_youxiaobi","parent":"a_youdabi","x":47.95,"y":0.74,"rotation":4.95,"length":43.6},{"name":"a_zuotuijin2","parent":"a_zuotuijin","x":0.16,"y":0.81,"rotation":60.79,"length":20.41},{"name":"a_zuoxiaobi","parent":"a_zuodabi","x":47.32,"y":0.78,"rotation":4.5,"length":38.05},{"name":"bone12","parent":"bone5","x":-1.51,"y":-10.47,"rotation":-145.99,"length":10.77},{"name":"bone15","parent":"bone5","x":-2.42,"y":-20.81,"rotation":-143.49,"length":12.84},{"name":"bone18","parent":"bone5","x":-1.76,"y":-26.82,"rotation":-129.84,"length":13.11},{"name":"bone21","parent":"bone5","x":2.14,"y":-26.28,"rotation":-102.09,"length":14.67},{"name":"bone24","parent":"bone5","x":4.43,"y":-13.57,"rotation":-59.57,"length":11.57},{"name":"bone26","parent":"bone5","x":4.89,"y":-3.82,"rotation":-36.5,"length":9.99},{"name":"bone28","parent":"bone5","x":3.22,"y":4.75,"rotation":57.47,"length":7.4},{"name":"bone30","parent":"bone29","x":15.94,"y":0.05,"rotation":28.86,"length":9.04},{"name":"bone33","parent":"bone32","x":9.22,"rotation":-26.38,"length":9.62},{"name":"bone36","parent":"bone35","x":10.26,"y":0.02,"rotation":-13.39,"length":10.05},{"name":"bone39","parent":"bone38","x":13.65,"y":0.06,"rotation":-27.1,"length":10.68},{"name":"bone4","parent":"a_youtuijin","x":-1.71,"y":-2.57,"rotation":-100.34,"length":23.59},{"name":"bone42","parent":"bone41","x":12.39,"y":-0.13,"rotation":-28.86,"length":9.91},{"name":"bone45","parent":"bone44","x":17.55,"y":-0.08,"rotation":11.56,"length":10.83},{"name":"bone6","parent":"bone5","x":-3.63,"y":7.4,"rotation":142.06,"length":11.67},{"name":"bone9","parent":"bone5","x":-5.52,"y":1.43,"rotation":171.42,"length":12.41},{"name":"u_jiyi2_jienuosi4XT","parent":"a_youtuijin","x":26.03,"y":10.69,"rotation":-12.0,"length":23.42},{"name":"u_jiyi4_jienuosi4XT","parent":"a_youtuijin","x":54.4,"y":12.31,"rotation":-15.82,"length":14.25},{"name":"a_youshou","parent":"a_youxiaobi","x":44.42,"y":-0.48,"rotation":-21.87,"length":37.24},{"name":"a_zuoshou","parent":"a_zuoxiaobi","x":38.6,"y":-0.86,"rotation":49.39,"length":32.43},{"name":"bone10","parent":"bone9","x":12.85,"y":0.07,"rotation":7.68,"length":8.24},{"name":"bone13","parent":"bone12","x":10.77,"y":-0.01,"rotation":-14.14,"length":8.49},{"name":"bone16","parent":"bone15","x":13.05,"y":0.03,"rotation":-15.4,"length":10.83},{"name":"bone19","parent":"bone18","x":13.12,"rotation":-23.03,"length":10.87},{"name":"bone22","parent":"bone21","x":14.7,"y":-0.14,"rotation":-23.19,"length":12.19},{"name":"bone25","parent":"bone24","x":11.57,"y":-0.01,"rotation":-3.6,"length":9.45},{"name":"bone27","parent":"bone26","x":9.99,"y":-0.03,"rotation":-7.62,"length":8.27},{"name":"bone31","parent":"bone30","x":9.15,"y":0.02,"rotation":17.07,"length":11.34},{"name":"bone34","parent":"bone33","x":9.65,"y":-0.14,"rotation":-13.82,"length":7.7},{"name":"bone37","parent":"bone36","x":10.06,"y":-0.1,"rotation":-17.48,"length":11.29},{"name":"bone40","parent":"bone39","x":10.68,"y":-0.01,"rotation":-9.38,"length":11.23},{"name":"bone43","parent":"bone42","x":10.02,"y":-0.05,"rotation":-14.56,"length":11.33},{"name":"bone46","parent":"bone45","x":10.83,"y":0.04,"rotation":4.95,"length":8.56},{"name":"bone7","parent":"bone6","x":11.9,"y":0.15,"rotation":18.7,"length":11.19},{"name":"Penhuo","parent":"a_youshou","x":11.2,"y":7.83,"rotation":354.15,"length":43.84,"transform":"noRotationOrReflection"},{"name":"Penhuo2","parent":"a_zuoshou","x":11.76,"y":0.75,"rotation":13.35,"scaleX":0.941,"scaleY":0.941,"length":43.84,"transform":"noRotationOrReflection"},{"name":"bone11","parent":"bone10","x":8.24,"rotation":12.43,"length":6.91},{"name":"bone14","parent":"bone13","x":8.77,"y":-0.11,"rotation":-17.89,"length":9.76},{"name":"bone17","parent":"bone16","x":11.25,"y":-0.17,"rotation":-21.09,"length":10.35},{"name":"bone20","parent":"bone19","x":11.07,"y":0.05,"rotation":-16.36,"length":11.94},{"name":"bone23","parent":"bone22","x":12.27,"y":-0.13,"rotation":-17.07,"length":11.85},{"name":"bone47","parent":"bone46","x":8.56,"y":0.01,"rotation":7.62,"length":10.47},{"name":"bone8","parent":"bone7","x":11.47,"y":0.17,"rotation":8.57,"length":13.68},{"name":"guangqiu_jienuosi4XT","parent":"Penhuo2","x":-3.57,"y":-2.25,"rotation":-88.18,"length":19.07},{"name":"guangqiu_jienuosi4XT2","parent":"Penhuo2","x":-3.57,"y":-2.25,"rotation":-88.18,"length":19.07},{"name":"guangqiu_jienuosi4XT3","parent":"Penhuo","x":-1.11,"y":-5.21,"rotation":-96.17,"scaleX":0.941,"scaleY":0.941,"length":19.07},{"name":"guangqiu_jienuosi4XT4","parent":"Penhuo","x":-1.11,"y":-5.21,"rotation":-96.17,"scaleX":0.941,"scaleY":0.941,"length":19.07},{"name":"texiao_1_jienuosi4XT","parent":"Penhuo","x":-0.96,"y":0.11,"rotation":5.84},{"name":"texiao_1_jienuosi4XT2","parent":"Penhuo","x":-0.96,"y":0.11,"rotation":5.84},{"name":"texiao_1_jienuosi4XT3","parent":"Penhuo","x":-0.96,"y":0.11,"rotation":5.84},{"name":"texiao_1_jienuosi4XT4","parent":"Penhuo","x":-0.96,"y":0.11,"rotation":5.84},{"name":"texiao_1_jienuosi4XT5","parent":"Penhuo2","x":-0.96,"y":0.11,"rotation":5.84},{"name":"texiao_1_jienuosi4XT6","parent":"Penhuo2","x":-0.96,"y":0.11,"rotation":5.84},{"name":"texiao_1_jienuosi4XT7","parent":"Penhuo2","x":-0.96,"y":0.11,"rotation":5.84},{"name":"texiao_1_jienuosi4XT8","parent":"Penhuo2","x":-0.96,"y":0.11,"rotation":5.84}],"slots":[{"name":"canying_jienuosi4XT","bone":"canying_jienuosi4XT","blend":"additive"},{"name":"texiao_4_jienuosi4XT","bone":"texiao_4_jienuosi4XT","attachment":"texiao_4_jienuosi4XT"},{"name":"texiao_4_jienuosi4XT5","bone":"texiao_4_jienuosi4XT5","attachment":"texiao_4_jienuosi4XT"},{"name":"texiao_4_jienuosi4XT3","bone":"texiao_4_jienuosi4XT3"},{"name":"texiao_4_jienuosi4XT7","bone":"texiao_4_jienuosi4XT7"},{"name":"texiao_4_jienuosi4XT2","bone":"texiao_4_jienuosi4XT2"},{"name":"texiao_4_jienuosi4XT6","bone":"texiao_4_jienuosi4XT6"},{"name":"texiao_4_jienuosi4XT4","bone":"texiao_4_jienuosi4XT4"},{"name":"texiao_4_jienuosi4XT8","bone":"texiao_4_jienuosi4XT8"},{"name":"a_zuotuijin2","bone":"a_zuotuijin","attachment":"a_zuotuijin_jienuosi4XT"},{"name":"guangqiu_jienuosi4XT5","bone":"guangqiu_jienuosi4XT3","color":"ff9a00ff","blend":"additive"},{"name":"guangqiu_jienuosi4XT6","bone":"guangqiu_jienuosi4XT6","color":"ff9a00ff","blend":"additive"},{"name":"bone4","bone":"a_youtuijin","attachment":"a_youtuijin_jienuosi4XT"},{"name":"a_youtuijin22","bone":"a_youtuijin22","attachment":"a_youtuijin22_jienuosi4XT"},{"name":"a_zuojiao","bone":"a_zuojiao","attachment":"a_zuojiao_jienuosi4XT"},{"name":"a_youjiao","bone":"a_youjiao","attachment":"a_youjiao_jienuosi4XT"},{"name":"a_zuoxioatui","bone":"a_zuoxioatui","attachment":"a_zuoxioatui_jienuosi4XT"},{"name":"a_zuodatui","bone":"a_zuodatui","attachment":"a_zuodatui_jienuosi4XT"},{"name":"a_kua","bone":"a_kua","attachment":"a_kua_jienuosi4XT"},{"name":"a_youxiaotui","bone":"a_youxiaotui","attachment":"a_youxiaotui_jienuosi4XT"},{"name":"texiao_1_jienuosi4XT5","bone":"texiao_1_jienuosi4XT5","attachment":"texiao_1_jienuosi4XT"},{"name":"texiao_1_jienuosi4XT7","bone":"texiao_1_jienuosi4XT7"},{"name":"texiao_1_jienuosi4XT6","bone":"texiao_1_jienuosi4XT6"},{"name":"texiao_1_jienuosi4XT8","bone":"texiao_1_jienuosi4XT8"},{"name":"guangqiu_jienuosi4XT","bone":"guangqiu_jienuosi4XT","color":"ff9a00ff","blend":"additive"},{"name":"guangqiu_jienuosi4XT2","bone":"guangqiu_jienuosi4XT5","color":"ff9a00ff","blend":"additive"},{"name":"a_youdatui","bone":"a_youdatui","attachment":"a_youdatui_jienuosi4XT"},{"name":"a_zuoshou","bone":"a_zuoshou","attachment":"a_zuoshou_jienuosi4XT"},{"name":"a_zuoxiaobi","bone":"a_zuoxiaobi","attachment":"a_zuoxiaobi_jienuosi4XT"},{"name":"a_zuodabi","bone":"a_zuodabi","attachment":"a_zuodabi_jienuosi4XT"},{"name":"a_shenti","bone":"a_shenti","attachment":"a_shenti_jienuosi4XT"},{"name":"a_cheek","bone":"a_cheek","attachment":"a_hair4_jienuosi4XT"},{"name":"a_cheek__1","bone":"a_cheek","attachment":"a_cheek_jienuosi4XT"},{"name":"a_cheek__2","bone":"a_cheek","attachment":"a_hair3_jienuosi4XT"},{"name":"a_cheek__3","bone":"a_cheek","attachment":"a_hair2_jienuosi4XT"},{"name":"a_cheek__4","bone":"a_cheek","attachment":"a_hair1_jienuosi4XT"},{"name":"a_youdabi","bone":"a_youdabi","attachment":"a_youdabi_jienuosi4XT"},{"name":"a_youxiaobi","bone":"a_youxiaobi","attachment":"a_youxiaobi_jienuosi4XT"},{"name":"texiao_1_jienuosi4XT","bone":"texiao_1_jienuosi4XT","attachment":"texiao_1_jienuosi4XT"},{"name":"texiao_1_jienuosi4XT3","bone":"texiao_1_jienuosi4XT3"},{"name":"texiao_1_jienuosi4XT2","bone":"texiao_1_jienuosi4XT2"},{"name":"texiao_1_jienuosi4XT4","bone":"texiao_1_jienuosi4XT4"},{"name":"guangqiu_jienuosi4XT3","bone":"guangqiu_jienuosi4XT2","color":"ff9a00ff","blend":"additive"},{"name":"guangqiu_jienuosi4XT4","bone":"guangqiu_jienuosi4XT6","color":"ff9a00ff","blend":"additive"},{"name":"a_youshou","bone":"a_youshou","attachment":"a_youshou_jienuosi4XT"},{"name":"bone","bone":"bone"},{"name":"a_zuoxiaobi__1","bone":"a_zuoxiaobi"},{"name":"u_jiyi2_jienuosi4XT","bone":"u_jiyi2_jienuosi4XT"},{"name":"u_jiyi4_jienuosi4XT","bone":"u_jiyi4_jienuosi4XT"},{"name":"bone__1","bone":"bone"}],"skins":[{"name":"default","attachments":{"a_zuotuijin2":{"a_zuotuijin_jienuosi4XT":{"type":"region","x":8.42,"y":0.89,"rotation":-74.24,"width":14.0,"height":23.0}},"bone4":{"a_youtuijin_jienuosi4XT":{"type":"region","x":8.71,"y":0.95,"rotation":-74.03,"width":15.0,"height":29.0}},"a_youtuijin22":{"a_youtuijin22_jienuosi4XT":{"type":"region","x":12.02,"y":1.11,"rotation":-125.28,"width":23.0,"height":29.0}},"a_zuojiao":{"a_zuojiao_jienuosi4XT":{"type":"region","x":11.73,"y":-1.57,"rotation":87.29,"width":23.0,"height":41.0}},"a_youjiao":{"a_youjiao_jienuosi4XT":{"type":"region","x":14.43,"y":-0.77,"rotation":87.95,"width":22.0,"height":42.0}},"a_zuoxioatui":{"a_zuoxioatui_jienuosi4XT":{"type":"mesh","uvs":[0.59276,0.0,0.4136,0.13223,0.19086,0.34053,0.0,0.62695,0.0,0.85087,0.17149,0.92378,0.28286,1.0,0.40876,1.0,0.50076,0.85608,0.64118,0.67381,0.8397,0.49155,1.0,0.34574,1.0,0.0],"triangles":[0,12,11,10,0,11,1,0,10,9,1,10,2,1,9,8,3,2,3,5,4,2,9,8,8,5,3,6,5,8,7,6,8],"vertices":[4.68,-20.36,17.26,-21.21,34.06,-20.22,51.94,-14.84,59.19,-5.44,53.81,3.58,51.24,10.65,45.56,15.03,36.75,12.19,24.51,9.43,9.65,8.69,-2.29,8.15,-13.48,-6.36],"hull":13,"edges":[0,2,2,4,4,6,6,8,8,10,10,12,12,14,14,16,16,18,18,20,20,22,22,24,0,24],"width":13.0,"height":57.0}},"a_zuodatui":{"a_zuodatui_jienuosi4XT":{"type":"region","x":21.54,"y":-0.91,"rotation":83.26,"width":31.0,"height":78.0}},"a_kua":{"a_kua_jienuosi4XT":{"type":"region","x":2.02,"y":-4.21,"rotation":90.45,"width":54.0,"height":35.0}},"a_youxiaotui":{"a_youxiaotui_jienuosi4XT":{"type":"region","x":26.82,"y":-1.2,"rotation":101.67,"width":37.0,"height":71.0}},"a_youdatui":{"a_youdatui_jienuosi4XT":{"type":"region","x":26.85,"y":2.22,"rotation":107.07,"width":42.0,"height":72.0}},"a_zuoshou":{"a_zuoshou_jienuosi4XT":{"type":"region","x":14.1,"y":-3.05,"rotation":27.14,"width":43.0,"height":28.0}},"a_zuoxiaobi":{"a_zuoxiaobi_jienuosi4XT":{"type":"region","x":13.55,"y":-0.87,"rotation":76.54,"width":31.0,"height":59.0}},"a_zuodabi":{"a_zuodabi_jienuosi4XT":{"type":"region","x":19.55,"y":-7.69,"rotation":81.05,"width":49.0,"height":68.0}},"a_shenti":{"a_shenti_jienuosi4XT":{"type":"mesh","uvs":[0.48931,0.0,0.29719,0.0,0.27697,0.1044,0.11182,0.1499,0.16912,0.21923,0.03431,0.24957,0.0,0.3449,0.0,0.4359,0.0,0.54857,0.06464,0.62657,0.13542,0.70673,0.20282,0.77173,0.25675,0.8649,0.25001,0.92773,0.25001,1.0,0.47245,1.0,0.71175,1.0,0.89712,1.0,1.0,1.0,1.0,0.90607,0.99823,0.80857,0.99823,0.69807,1.0,0.6114,1.0,0.50957,1.0,0.38823,0.96116,0.3124,0.99149,0.23223,0.85331,0.2084,0.75219,0.1629,0.73197,0.0589,0.70164,0.0,0.51964,0.10873,0.57694,0.23657,0.63086,0.31457,0.6949,0.41423,0.72523,0.5269,0.74208,0.6374,0.73871,0.74573,0.72186,0.85407,0.71512,0.9429,0.48594,0.91907,0.49268,0.8194,0.47919,0.7089,0.44549,0.59407,0.40505,0.4749,0.34101,0.36873,0.24664,0.28207,0.84656,0.3189,0.86679,0.4164,0.87016,0.50523,0.88027,0.63307,0.88027,0.75223,0.8769,0.86057,0.88364,0.93423],"triangles":[11,10,43,43,10,44,43,35,36,50,36,49,36,35,49,50,49,22,45,9,8,10,9,44,9,45,44,45,8,46,4,6,5,4,46,6,49,23,22,43,34,35,43,44,34,46,8,7,35,48,49,35,34,48,23,48,24,23,49,48,44,33,34,44,32,33,44,45,32,46,7,6,34,47,48,48,25,24,48,47,25,34,33,47,46,2,45,45,2,31,45,31,32,0,2,1,2,0,31,33,28,47,47,27,25,47,28,27,33,32,28,25,27,26,46,4,2,32,31,28,4,3,2,31,29,28,31,30,29,31,0,30,18,53,19,16,53,17,16,39,53,53,39,52,39,38,52,18,17,53,15,40,16,16,40,39,40,15,13,15,14,13,39,40,38,53,52,19,13,12,40,40,41,38,40,12,41,52,20,19,41,12,42,38,37,52,52,51,20,52,37,51,38,41,37,12,11,42,41,42,37,51,21,20,42,11,43,37,36,51,36,50,51,51,50,21,37,42,36,42,43,36,21,50,22],"vertices":[1,10,79.76,2.14,1.0,1,10,82.18,17.51,1.0,1,10,69.44,21.18,1.0,1,10,65.86,35.28,1.0,2,5,95.88,40.46,0.0001,10,56.51,32.06,0.99989,2,5,92.06,51.38,0.00359,10,54.44,43.44,0.9964,2,5,80.04,54.16,0.02138,10,43.0,48.06,0.97861,2,5,68.58,54.16,0.06827,10,31.68,49.84,0.93172,2,5,54.38,54.16,0.16472,10,17.65,52.05,0.83527,2,5,44.55,48.93,0.28799,10,7.13,48.41,0.71199,2,5,34.45,43.19,0.48826,10,-3.73,44.32,0.51173,2,5,26.26,37.73,0.69996,10,-12.67,40.2,0.30003,2,5,14.52,33.37,0.91963,10,-24.95,37.71,0.08036,2,5,6.61,33.91,0.98158,10,-32.68,39.48,0.0184,2,5,-2.49,33.91,0.99897,10,-41.68,40.9,0.00102,1,5,-2.49,15.89,1.0,1,5,-2.49,-3.48,1.0,1,5,-2.49,-18.49,1.0,1,5,-2.49,-26.83,1.0,1,5,9.34,-26.83,1.0,2,5,21.62,-26.68,0.96863,10,-27.28,-22.71,0.03136,2,5,35.54,-26.68,0.77525,10,-13.53,-24.88,0.22474,2,5,46.46,-26.83,0.48091,10,-2.76,-26.72,0.51908,2,5,59.3,-26.83,0.17047,10,9.9,-28.72,0.82952,2,5,74.58,-26.83,0.0209,10,25.0,-31.1,0.97909,2,5,84.14,-23.68,0.00085,10,34.93,-29.48,0.99914,1,10,44.53,-33.48,1.0,1,10,49.23,-22.89,1.0,1,10,56.17,-15.69,1.0,1,10,69.37,-16.11,1.0,1,10,77.09,-14.84,1.0,1,10,65.85,1.85,1.0,1,10,49.21,-0.22,1.0,1,10,38.82,-3.01,1.0,2,5,71.31,-2.11,0.00307,10,25.61,-6.18,0.99692,2,5,57.11,-4.57,0.08445,10,11.21,-6.39,0.91554,2,5,43.19,-5.94,0.65039,10,-2.75,-5.58,0.3496,2,5,29.54,-5.66,0.99204,10,-16.19,-3.18,0.00795,1,5,15.89,-4.3,1.0,1,5,4.7,-3.75,1.0,1,5,7.7,14.8,1.0,2,5,20.26,14.26,0.96821,10,-22.26,17.94,0.03178,2,5,34.18,15.35,0.75868,10,-8.33,16.85,0.24131,2,5,48.65,18.08,0.26693,10,6.37,17.3,0.73306,2,5,63.66,21.35,0.06451,10,21.72,18.2,0.93548,2,5,77.04,26.54,0.0084,10,35.74,21.24,0.99159,2,5,87.96,34.18,0.0011,10,47.71,27.09,0.99888,1,10,35.57,-20.18,1.0,2,5,71.03,-16.04,0.01513,10,23.18,-19.89,0.98486,2,5,59.84,-16.31,0.10452,10,12.08,-18.42,0.89547,2,5,43.73,-17.13,0.57678,10,-3.95,-16.72,0.42321,2,5,28.72,-17.13,0.95087,10,-18.78,-14.38,0.04912,2,5,15.07,-16.86,0.99093,10,-32.22,-11.99,0.00906,1,5,5.79,-17.4,1.0],"hull":54,"edges":[0,2,2,4,4,6,6,8,8,10,10,12,12,14,14,16,16,18,18,20,20,22,22,24,24,26,26,28,28,30,30,32,36,38,38,40,40,42,42,44,44,46,46,48,48,50,50,52,52,54,54,56,56,58,58,60,0,60,0,62,62,64,64,66,66,68,68,70,70,72,72,74,74,76,76,78,78,32,30,80,80,82,82,84,84,86,86,88,88,90,90,92,92,8,54,94,94,96,96,98,98,100,100,102,102,104,104,106,32,34,34,36,106,34],"width":31.0,"height":81.0}},"a_cheek":{"a_hair4_jienuosi4XT":{"type":"mesh","uvs":[0.53649,0.0,0.24016,0.0,0.09728,0.08292,0.0,0.24411,0.0,0.40041,0.0,0.52986,0.0,0.67395,0.0,0.7863,0.09199,0.77897,0.13962,0.86445,0.27191,0.95238,0.37245,1.0,0.61587,1.0,0.64233,0.87422,0.77462,0.74722,0.9122,0.60313,1.0,0.43461,1.0,0.28807,1.0,0.10734,0.86458,0.0,0.36187,0.90841,0.36716,0.8034,0.36716,0.68616,0.40949,0.53718,0.47828,0.36622,0.49945,0.22457,0.52591,0.09024],"triangles":[13,21,22,9,8,21,14,13,22,21,10,9,20,21,13,20,10,21,12,11,20,10,20,11,13,12,20,22,6,5,22,23,14,8,6,22,7,6,8,8,22,21,23,5,4,24,23,4,23,22,5,14,23,15,26,1,0,2,1,26,26,0,19,18,26,19,25,2,26,3,2,25,26,18,17,25,26,17,24,3,25,4,3,24,24,25,17,16,24,17,15,24,16,23,24,15],"vertices":[1,27,-3.0,1.19,1.0,1,27,-1.42,-5.73,1.0,1,27,3.54,-8.11,1.0,2,27,12.23,-8.52,0.91571,56,-6.9,-7.19,0.08428,3,27,20.16,-6.71,0.21918,56,1.21,-7.01,0.78058,75,-10.18,-6.2,0.00023,3,27,26.72,-5.21,0.00116,56,7.94,-6.86,0.83934,75,-3.46,-6.63,0.15948,3,56,15.43,-6.69,0.1401,75,4.0,-7.11,0.81788,84,-5.46,-6.46,0.04201,3,56,21.27,-6.56,0.00362,75,9.83,-7.49,0.69322,84,0.26,-7.61,0.30314,3,56,20.84,-4.36,0.00064,75,9.59,-5.26,0.59846,84,0.32,-5.37,0.40088,2,75,14.1,-4.4,0.05308,84,4.9,-5.12,0.94691,2,27,46.68,6.03,0.0,84,10.0,-2.9,1.0,4,27,48.56,8.93,0.0,56,32.18,2.62,0.0,75,21.49,0.72,0.0,84,12.9,-1.02,0.99999,2,56,32.05,8.46,0.0,84,14.05,4.7,1.0,3,27,40.74,13.79,0.00256,75,15.38,7.6,0.04136,84,7.76,6.61,0.95606,4,27,33.6,15.42,0.06753,56,18.83,11.97,0.02886,75,8.99,11.19,0.39731,84,1.9,11.01,0.50628,4,27,25.56,16.97,0.36754,56,11.26,15.1,0.16617,75,1.73,14.96,0.37028,84,-4.79,15.72,0.09599,4,27,16.55,17.07,0.81188,56,2.45,17.01,0.09916,75,-6.88,17.62,0.08715,84,-12.97,19.5,0.00178,3,27,9.12,15.37,0.98091,56,-5.16,16.84,0.00922,75,-14.48,18.11,0.00985,1,27,-0.04,13.28,1.0,1,27,-4.75,8.87,1.0,1,84,8.18,-0.33,1.0,1,84,2.85,0.85,1.0,3,27,32.68,5.18,0.00461,75,5.2,1.63,0.94131,84,-3.12,2.04,0.05406,3,27,24.9,4.44,0.0288,56,8.1,2.96,0.84677,75,-2.46,3.14,0.12442,3,27,15.87,4.07,0.83955,56,-0.81,4.42,0.1584,75,-11.22,5.35,0.00203,1,27,8.57,2.93,1.0,1,27,1.62,1.99,1.0],"hull":27,"edges":[2,4,4,6,6,8,8,10,10,12,12,14,14,16,16,18,18,20,20,22,22,24,24,26,26,28,28,30,30,32,32,34,34,36,36,38,22,40,40,42,42,44,44,46,46,48,48,50,50,52,2,0,0,38,52,0,52,4,6,50,48,32,30,46,52,36],"width":20.0,"height":24.0}},"a_cheek__1":{"a_cheek_jienuosi4XT":{"type":"region","x":30.19,"y":-0.37,"rotation":-90.88,"width":61.0,"height":67.0}},"a_cheek__2":{"a_hair3_jienuosi4XT":{"type":"mesh","uvs":[0.0,0.13578,0.0,0.38022,0.15269,0.52933,0.38148,0.67111,0.5962,0.84222,0.65604,1.0,0.85316,1.0,0.9658,0.83244,1.0,0.698,1.0,0.46089,0.9658,0.26534,0.74052,0.13578,0.31812,0.0,0.15269,0.0,0.22661,0.21889,0.50468,0.34845,0.71236,0.49756,0.8426,0.64178,0.8778,0.808],"triangles":[3,2,15,2,14,15,2,1,14,16,15,11,1,0,14,14,12,15,15,12,11,0,13,14,14,13,12,4,3,16,3,15,16,17,16,9,16,10,9,16,11,10,6,18,7,6,5,18,5,4,18,4,17,18,4,16,17,7,18,8,18,17,8,17,9,8],"vertices":[1,26,-4.3,-0.81,1.0,2,55,-6.55,-12.86,0.03249,26,0.43,-8.23,0.9675,3,74,-6.69,-14.15,0.01455,55,-0.01,-12.07,0.24242,26,6.54,-10.69,0.74301,3,74,-0.36,-9.83,0.28325,55,7.19,-9.48,0.54087,26,14.11,-11.91,0.17587,3,74,6.91,-6.1,0.95769,55,15.17,-7.7,0.04157,26,21.95,-14.21,0.00072,1,74,12.78,-6.02,1.0,1,74,13.97,-1.23,1.0,1,74,8.79,2.94,1.0,2,74,4.3,4.94,0.91946,55,15.43,3.64,0.08053,3,74,-3.98,7.0,0.10445,55,7.93,7.72,0.88183,26,23.06,2.79,0.0137,2,55,1.33,10.33,0.78197,26,18.55,8.26,0.21802,2,55,-5.45,7.6,0.31509,26,11.29,9.16,0.6849,1,26,-0.23,7.58,1.0,1,26,-3.72,5.36,1.0,1,26,2.07,-0.28,1.0,1,26,10.45,-0.46,1.0,1,55,5.65,0.77,1.0,2,74,1.39,1.61,0.60943,55,11.77,1.15,0.39056,1,74,7.41,1.02,1.0],"hull":19,"edges":[0,2,2,4,4,6,6,8,8,10,10,12,12,14,14,16,16,18,18,20,20,22,22,24,24,26,0,26,0,28,28,30,30,32,32,34,34,36,36,12],"width":14.0,"height":25.0}},"a_cheek__3":{"a_hair2_jienuosi4XT":{"type":"mesh","uvs":[0.11872,0.19965,0.03928,0.38616,0.0,0.53149,0.0,0.68409,0.0,0.85122,0.06145,0.936,0.23142,0.99897,0.20555,0.90935,0.18708,0.7834,0.18523,0.6962,0.23327,0.65744,0.2776,0.74706,0.31455,0.827,0.39954,0.81004,0.45865,0.79066,0.44018,0.86333,0.4956,0.8488,0.55472,0.79793,0.55103,0.88755,0.51038,1.0,0.62308,1.0,0.71914,0.94569,0.77826,0.86575,0.83369,0.75433,0.82814,0.85122,0.77272,1.0,0.90389,1.0,0.97224,0.89724,1.0,0.74706,1.0,0.57267,1.0,0.33529,0.90758,0.14394,0.7487,0.01071,0.59536,0.0,0.47713,0.0,0.37921,0.0,0.23511,0.06885,0.23327,0.51453,0.27576,0.25778,0.66926,0.13909,0.75055,0.29653,0.81521,0.48547,0.83553,0.6308,0.58613,0.62595,0.57135,0.44429,0.5344,0.20691],"triangles":[39,32,31,40,31,30,41,40,30,41,30,29,42,41,29,43,41,42,42,29,28,23,42,28,28,24,23,27,24,28,26,24,27,25,24,26,17,43,23,23,22,17,21,18,17,22,21,17,20,18,21,19,18,20,43,44,41,23,43,42,39,33,32,40,39,31,40,44,45,40,45,39,44,40,41,45,34,33,45,33,39,35,34,45,38,35,45,44,38,45,43,10,44,10,14,11,43,14,10,17,14,43,13,11,14,12,11,13,16,14,17,15,14,16,8,4,3,5,4,8,7,5,8,5,7,6,44,10,37,9,2,37,9,3,2,37,10,9,8,3,9,38,36,35,0,36,38,38,1,0,37,1,38,2,1,37,37,38,44],"vertices":[3,22,2.0,-6.23,0.99999,52,-9.43,-35.26,0.0,25,-18.43,-36.26,0.0,2,22,11.61,-6.36,0.90463,50,-6.89,-3.53,0.09536,2,22,18.47,-5.3,0.38572,50,-0.37,-5.91,0.61426,4,22,24.51,-2.04,0.00218,50,6.49,-5.97,0.81311,70,-4.3,-4.95,0.1847,23,16.48,-31.49,0.0,7,50,14.01,-6.04,0.16847,70,2.86,-7.22,0.83152,71,22.74,-17.39,0.0,51,27.58,-22.47,0.0,23,23.95,-32.37,0.0,52,20.33,-40.01,0.0,72,21.77,-34.98,0.0,2,22,32.77,6.53,0.0,70,7.59,-4.91,0.99999,5,22,30.5,16.7,3e-05,50,20.78,7.55,0.00105,70,13.32,3.78,0.9989,51,29.25,-7.37,0.0,23,32.15,-19.59,0.0,2,70,9.02,3.54,0.99999,23,27.97,-20.63,0.0,7,22,23.2,9.79,0.005,50,11.06,5.02,0.14812,70,3.29,4.22,0.83375,71,14.11,-9.87,0.01038,51,20.99,-13.1,0.00272,52,16.44,-29.23,0.0,72,14.83,-25.87,0.0,8,22,19.8,7.83,0.06259,50,7.13,4.95,0.59587,70,-0.48,5.3,0.23072,71,10.89,-12.13,0.08409,51,17.34,-14.52,0.02632,23,18.3,-20.7,0.00035,52,12.54,-29.64,0.0,72,11.23,-27.43,1e-05,8,22,16.92,9.5,0.16178,50,5.42,7.8,0.37354,70,-1.28,8.53,0.02886,71,7.87,-10.72,0.32491,51,14.74,-12.44,0.1026,23,16.9,-17.68,0.00823,52,10.58,-26.95,0.0,72,8.55,-25.45,4e-05,7,22,19.23,13.71,0.05309,50,9.47,10.37,0.11768,70,3.34,9.8,0.00167,71,9.8,-6.32,0.7758,51,17.66,-8.62,0.05156,52,14.4,-24.03,0.0,72,11.32,-21.52,0.00016,3,22,21.36,17.34,0.00976,50,13.09,12.52,0.03237,71,11.59,-2.51,0.95786,5,70,8.22,15.8,0.0,71,8.19,1.24,0.9859,51,17.91,-0.89,1e-05,52,16.68,-16.64,0.00074,72,11.28,-13.79,0.01332,5,70,8.44,19.39,0.0,71,5.54,3.67,0.8234,51,15.91,2.09,0.01706,52,15.54,-13.23,0.00937,72,9.17,-10.87,0.15016,4,70,11.23,17.36,0.0,71,8.87,4.56,0.81378,52,18.89,-14.07,0.00411,72,12.61,-10.67,0.1821,5,70,11.59,20.68,0.0,71,6.52,6.93,0.74093,51,17.64,5.02,0.01593,52,17.99,-10.86,0.01151,72,10.78,-7.88,0.23159,5,70,10.46,24.7,0.0,71,2.69,8.57,0.30205,51,14.31,7.54,0.06609,52,15.44,-7.56,0.03862,72,7.36,-5.49,0.59323,5,70,14.24,23.27,0.0,71,6.17,10.62,0.04306,51,18.19,8.69,0.00567,52,19.48,-7.47,0.00119,72,11.19,-4.19,0.95006,1,72,16.78,-4.54,1.0,2,24,33.15,-8.34,0.0,72,14.3,1.63,0.99999,3,24,31.62,-2.36,3e-05,72,9.92,5.98,0.98965,73,13.44,-10.18,0.0103,6,70,17.36,36.35,0.0,24,28.61,1.64,8e-05,52,17.47,5.82,0.06168,72,5.29,7.87,0.85201,73,9.39,-7.24,0.07481,53,18.77,-8.68,0.0114,4,52,12.22,8.69,0.14487,72,-0.57,9.04,0.22843,73,3.96,-4.71,0.50948,53,13.83,-5.31,0.1172,3,52,16.6,8.7,0.01233,72,3.58,10.36,0.02194,73,8.33,-4.42,0.96571,1,73,15.42,-6.7,1.0,1,73,14.32,0.95,1.0,2,73,9.17,4.28,0.99663,53,20.43,2.72,0.00336,2,73,2.25,4.95,0.73012,53,13.71,4.5,0.26987,4,23,18.4,27.68,0.0,73,-5.51,3.84,0.065,53,5.86,4.67,0.91612,25,21.01,1.55,0.01885,5,23,7.79,28.93,2e-05,52,-7.32,17.04,2e-05,72,-21.73,11.13,3e-05,53,-4.81,4.9,0.15082,25,11.6,6.62,0.84908,2,72,-27.69,2.87,0.0,25,1.44,5.9,0.99999,4,51,-22.89,6.4,0.0,23,-8.44,15.91,0.07951,24,-9.65,5.93,0.34431,25,-8.28,0.49,0.57616,5,22,-19.25,14.25,0.01043,51,-20.3,-2.27,0.0,23,-9.98,6.98,0.49962,24,-11.54,-2.92,0.40124,25,-13.0,-7.24,0.08869,5,22,-15.94,8.11,0.13067,51,-17.95,-8.84,0.0,23,-10.79,0.05,0.75348,24,-12.64,-9.81,0.11176,25,-16.31,-13.38,0.00405,3,22,-13.19,3.02,0.35015,23,-11.47,-5.67,0.63877,24,-13.54,-15.51,0.01107,4,22,-6.43,-2.98,0.83921,23,-9.38,-14.48,0.16077,52,-15.82,-28.87,0.0,25,-20.35,-27.42,1e-05,8,22,11.26,6.44,0.38163,50,-1.01,7.85,0.27197,70,-7.41,10.47,0.00101,71,2.51,-14.27,0.19775,51,8.68,-14.6,0.1226,23,10.51,-16.93,0.02499,52,4.17,-27.44,0.0,72,2.58,-27.84,1e-05,5,22,-0.09,3.16,0.73315,71,-8.5,-18.55,0.00771,51,-3.03,-16.13,0.05672,23,-0.66,-13.09,0.20239,25,-11.73,-29.34,0.0,3,23,-3.25,10.58,0.21084,24,-4.68,0.4,0.67713,25,-5.42,-6.37,0.11202,2,24,3.06,4.03,0.86324,25,3.09,-5.51,0.13675,7,23,13.23,17.31,0.0,24,12.05,6.47,0.09024,52,0.24,6.68,0.29221,72,-11.4,3.53,0.00187,73,-7.85,-7.5,0.01048,53,1.71,-6.14,0.45985,25,12.38,-6.18,0.14531,5,24,18.7,6.63,0.01482,52,6.67,8.38,0.24571,72,-5.78,7.08,0.06071,73,-1.55,-5.39,0.17971,53,8.27,-5.08,0.49904,7,70,3.65,28.8,0.0,71,-4.78,5.85,0.04099,51,6.4,6.68,0.40524,23,17.93,3.15,0.01524,24,16.18,-7.86,0.03576,52,7.58,-6.3,0.38941,72,-0.5,-6.65,0.11333,5,51,-0.99,3.11,0.26657,23,9.71,3.24,0.42548,24,7.97,-7.44,0.20951,52,-0.49,-7.8,0.09804,72,-7.76,-10.51,0.00038,3,23,-1.15,2.32,0.79195,24,-2.91,-7.93,0.20799,25,-6.51,-14.82,5e-05],"hull":46,"edges":[0,2,2,4,4,6,6,8,8,10,10,12,12,14,14,16,16,18,18,20,20,22,22,24,24,26,26,28,28,30,30,32,32,34,34,36,36,38,38,40,40,42,42,44,44,46,46,48,48,50,50,52,52,54,54,56,56,58,58,60,60,62,62,64,64,66,70,72,0,72,20,74,74,76,76,70,66,78,78,80,80,82,82,84,84,46,34,86,86,88,88,90,66,68,68,70,90,68],"width":37.0,"height":59.0}},"a_cheek__4":{"a_hair1_jienuosi4XT":{"type":"mesh","uvs":[0.13453,0.17978,0.06965,0.3063,0.01645,0.4659,0.0,0.63135,0.0,0.81626,0.02164,1.0,0.08652,1.0,0.11766,0.86492,0.17086,0.97197,0.21628,1.0,0.2072,0.88438,0.2591,1.0,0.32788,1.0,0.30711,0.94861,0.29933,0.83961,0.37459,0.8727,0.35383,0.73645,0.37718,0.66638,0.42001,0.73061,0.43428,0.86297,0.46542,0.83378,0.50046,0.74813,0.50046,0.82404,0.4784,0.92526,0.51733,0.90969,0.55366,0.87076,0.54717,0.96224,0.59908,0.94667,0.64449,0.8766,0.62503,1.0,0.68212,1.0,0.71716,0.93693,0.74571,0.81042,0.7496,0.90579,0.76387,1.0,0.82226,0.97197,0.84951,0.88633,0.87157,0.7637,0.91829,0.88049,0.93256,0.80847,0.92218,0.72478,0.91699,0.63524,0.96111,0.67806,1.0,0.71699,1.0,0.56759,0.97302,0.42161,0.93149,0.32429,0.86402,0.24059,0.80303,0.17052,0.75632,0.0985,0.70441,0.05958,0.59931,0.06541,0.53572,0.08682,0.54091,0.02259,0.52015,0.0,0.44359,0.0,0.37352,0.05763,0.32032,0.10434,0.29177,0.13938,0.28788,0.02065,0.23597,0.06736,0.21781,0.16468,0.21392,0.20361,0.28139,0.35932,0.19186,0.43913,0.15033,0.56759,0.12568,0.71162,0.3307,0.43134,0.35406,0.54034,0.40466,0.37295,0.48901,0.44886,0.54481,0.56175,0.56167,0.65712,0.57076,0.76807,0.40596,0.29704,0.51496,0.28536,0.60709,0.32623,0.7096,0.40993,0.78097,0.53645,0.83158,0.63961,0.61228,0.24059,0.68495,0.17052],"triangles":[42,44,43,42,41,44,41,78,44,78,45,44,78,46,45,78,77,46,77,47,46,47,81,48,77,70,76,70,75,76,76,80,77,80,81,77,47,77,81,76,75,80,34,33,35,35,33,36,33,32,36,36,32,37,38,37,39,37,32,79,37,40,39,79,32,72,40,79,41,40,37,79,72,78,79,72,71,78,79,78,41,71,77,78,30,29,31,31,29,28,27,25,28,31,28,32,32,28,73,77,71,70,27,26,25,22,24,23,24,22,25,28,25,73,25,22,73,19,18,20,20,18,21,22,21,73,21,72,73,32,73,72,21,18,72,18,17,72,17,71,72,17,68,71,68,70,71,70,67,69,70,68,67,70,69,75,75,69,74,69,63,74,52,51,80,80,51,81,81,49,48,81,50,49,81,51,50,74,52,75,75,52,80,52,74,56,52,55,54,55,52,56,52,54,53,74,62,58,74,58,57,74,57,56,61,60,58,58,60,59,17,65,68,11,13,12,13,11,10,9,8,10,8,7,10,10,14,13,14,10,66,10,7,66,14,16,15,14,66,16,16,66,17,6,5,7,5,4,7,7,4,66,4,3,66,65,17,66,66,3,65,3,2,65,65,64,68,64,67,68,65,2,64,2,1,64,63,64,1,63,1,62,62,1,0,58,62,61,64,63,67,67,63,69,74,63,62],"vertices":[1,49,9.38,-1.28,1.0,3,49,10.29,7.6,0.42052,57,1.5,-11.66,0.53839,76,-13.64,-7.85,0.04107,3,49,9.4,17.56,0.06139,57,11.32,-9.83,0.61707,76,-3.75,-9.28,0.32152,4,49,5.72,26.17,0.00166,57,19.55,-5.35,0.15512,76,5.47,-7.67,0.78843,85,-7.11,-6.85,0.05477,2,76,15.29,-4.4,0.32209,85,3.09,-5.09,0.6779,1,85,12.92,-1.55,1.0,1,85,11.99,3.81,1.0,4,76,14.76,5.83,0.13891,85,4.09,5.1,0.55027,63,10.9,-10.51,0.108,79,0.32,-10.83,0.20278,3,76,19.04,11.96,0.00972,85,9.24,10.52,0.13879,79,7.14,-7.76,0.85148,2,85,10.14,14.55,0.11735,79,9.49,-4.37,0.88264,4,76,13.43,13.31,0.02861,85,3.89,12.7,0.08267,63,11.99,-2.99,0.06985,79,3.0,-3.72,0.81884,1,79,10.26,-0.86,1.0,5,76,16.37,24.97,0.00019,85,8.54,23.79,0.00055,63,18.45,7.14,0.00759,79,11.5,4.78,0.99117,64,20.4,-21.1,0.00049,6,63,15.58,5.4,0.01921,79,8.32,3.69,0.97893,58,27.57,7.51,0.00013,43,22.05,-25.25,0.00034,64,17.09,-21.72,0.00113,80,14.55,-17.99,0.00022,6,63,9.47,4.74,0.36558,79,2.22,4.36,0.57585,58,21.61,6.04,0.02155,43,16.67,-22.3,0.01037,64,11.15,-20.17,0.02052,80,8.42,-18.34,0.00609,6,63,11.32,11.06,0.41299,79,5.38,10.14,0.48173,58,22.6,12.55,0.0357,43,21.8,-18.17,0.01741,64,15.12,-14.91,0.04013,80,10.59,-12.12,0.01201,6,63,3.69,9.32,0.50545,79,-2.43,10.08,0.13931,58,15.27,9.8,0.16642,43,14.55,-15.24,0.05941,64,7.37,-13.84,0.09151,80,2.88,-13.48,0.03788,7,28,-18.2,-7.99,0.00288,63,-0.22,11.28,0.18742,79,-5.84,12.83,0.01947,58,11.12,11.22,0.25397,43,12.45,-11.38,0.16168,64,4.4,-10.61,0.24165,80,-0.93,-11.33,0.13291,6,63,3.36,14.87,0.05125,79,-1.56,15.58,0.00179,58,14.2,15.27,0.07455,43,17.46,-10.49,0.05646,64,9.03,-8.52,0.27632,80,2.83,-7.92,0.53961,5,28,-29.28,-12.62,0.0001,63,10.78,16.08,0.01108,58,21.38,17.45,0.01377,64,16.39,-10.03,0.11995,80,10.29,-7.08,0.85507,6,28,-27.68,-15.26,3e-05,63,9.14,18.69,0.01758,58,19.41,19.82,0.02376,43,24.38,-10.66,0.00914,64,15.79,-7.0,0.15049,80,8.79,-4.39,0.79897,5,63,4.34,21.63,0.00627,58,14.26,22.09,0.00942,43,22.13,-5.5,0.00728,64,12.34,-2.55,0.08951,80,4.14,-1.21,0.88748,2,79,4.99,21.05,0.0,80,8.39,-1.42,0.99999,1,80,13.96,-3.55,1.0,2,58,23.04,24.71,0.0,80,13.25,-0.25,1.0,4,58,20.47,27.45,0.0,80,11.22,2.9,0.74776,65,13.69,-11.66,0.03087,81,6.41,-9.84,0.22135,3,58,25.62,27.59,0.0,80,16.31,2.1,0.65264,81,11.52,-10.46,0.34735,4,58,24.17,31.8,0.0,80,15.65,6.5,0.55035,65,19.06,-9.71,0.00801,81,10.72,-6.09,0.44163,4,58,19.77,35.05,0.0,80,11.92,10.51,0.12184,65,16.85,-4.71,0.00602,81,6.85,-2.21,0.87212,4,58,26.83,34.36,0.0,64,29.24,2.23,1e-05,65,22.65,-8.81,0.00215,81,13.74,-3.95,0.99782,3,58,26.19,39.11,0.0,64,30.94,6.72,0.0,81,13.81,0.83,0.99999,3,58,22.29,41.55,0.0,81,10.32,3.83,0.96121,82,12.48,-8.14,0.03878,5,58,14.95,42.98,0.0,65,16.59,4.55,0.05451,81,3.27,6.33,0.34647,66,15.62,-5.83,0.0235,82,6.02,-4.36,0.5755,4,58,20.2,44.02,0.0,65,21.67,2.86,0.00254,81,8.62,6.58,0.05504,82,11.32,-5.12,0.94241,3,58,25.27,45.92,0.0,81,13.91,7.7,0.01529,82,16.73,-5.0,0.9847,2,58,23.05,50.56,0.0,82,16.18,0.11,1.0,4,58,17.99,52.19,0.0,66,23.47,-0.12,0.00532,82,11.94,3.32,0.98139,83,16.19,-16.39,0.01327,4,58,10.94,53.1,0.0,66,18.27,4.73,0.09393,82,5.59,6.51,0.72413,83,11.97,-10.67,0.18193,6,58,16.89,57.87,0.0,81,7.42,20.77,0.0,66,25.89,5.13,0.03754,82,12.78,9.04,0.74502,67,27.52,-17.02,6e-05,83,19.53,-11.67,0.21736,4,58,12.73,58.52,0.0,66,22.89,8.08,0.05261,82,9.07,11.03,0.72987,83,17.12,-8.22,0.2175,4,58,8.21,57.02,0.0,66,18.34,9.51,0.09028,82,4.31,11.12,0.60664,83,12.91,-5.98,0.30306,4,58,3.3,55.92,0.0,66,13.71,11.48,0.0727,82,-0.68,11.7,0.20185,83,8.71,-3.2,0.72544,4,58,5.17,59.91,0.0,66,17.57,13.62,0.00162,82,2.4,14.85,0.00474,83,12.9,-1.79,0.99362,3,58,6.9,63.44,0.0,67,28.01,-5.59,0.00185,83,16.64,-0.6,0.99814,3,58,-1.39,62.32,0.0,67,23.28,1.3,0.0058,83,10.09,4.61,0.99419,3,58,-9.18,58.97,0.0,67,16.79,6.77,0.35889,83,2.28,7.92,0.6411,5,58,-14.11,54.78,0.0,68,23.39,-23.06,0.00211,46,28.32,4.12,0.02397,67,10.83,9.29,0.70892,83,-4.15,8.59,0.26497,5,58,-18.0,48.54,0.0,68,20.55,-16.28,0.05013,46,21.85,7.62,0.20926,67,3.5,9.95,0.70763,83,-11.34,7.07,0.03296,4,58,-21.2,42.93,0.0,68,17.83,-10.43,0.22195,46,16.06,10.47,0.3853,67,-2.94,10.29,0.39273,5,58,-24.66,38.5,0.0,47,27.46,-6.06,0.0001,68,16.23,-5.03,0.49105,46,11.43,13.66,0.34473,67,-8.45,11.4,0.1641,5,58,-26.24,33.89,0.0,47,24.86,-1.93,0.00041,68,13.38,-1.08,0.82662,46,6.72,14.95,0.12185,67,-13.28,10.73,0.0511,3,47,17.15,2.36,0.012,68,5.41,2.73,0.98761,67,-20.38,5.47,0.00037,5,28,14.04,-21.8,1e-05,58,-22.82,20.05,0.0,69,9.18,-7.81,0.30444,47,11.96,4.11,0.37412,68,0.12,4.14,0.32141,5,28,17.63,-22.29,0.0,69,12.1,-5.66,0.80142,47,14.2,6.96,0.09959,68,2.18,7.13,0.09898,67,-25.78,4.68,0.0,3,69,11.82,-3.52,0.99746,68,1.22,9.06,0.00253,67,-27.94,4.73,0.0,1,69,7.41,1.15,1.0,3,49,-4.11,-17.64,0.00105,48,11.44,3.02,0.37534,69,1.03,3.22,0.62359,3,49,-1.68,-13.07,0.09608,48,6.71,5.12,0.81171,69,-3.93,4.68,0.09219,3,28,11.41,-1.27,0.004,49,-0.67,-10.14,0.27426,48,3.72,5.93,0.72173,2,49,3.09,-15.63,0.32633,48,8.93,10.07,0.67366,2,49,5.43,-11.11,0.3544,48,4.26,12.09,0.64559,3,28,10.09,4.96,0.00794,49,3.87,-5.67,0.54827,48,-1.04,10.15,0.44378,3,28,7.91,5.32,0.02368,49,3.0,-3.64,0.74294,48,-3.01,9.15,0.23336,1,28,-0.88,-0.21,1.0,1,57,1.24,1.01,1.0,4,57,9.08,2.56,0.45605,76,-1.89,3.18,0.35023,63,-5.74,-7.77,0.06932,58,8.2,-8.4,0.12438,5,76,6.4,3.76,0.41948,85,-4.47,4.3,0.26986,63,2.31,-9.84,0.21458,79,-7.91,-8.33,0.08535,58,16.47,-9.37,0.01071,8,28,-4.98,-4.29,0.32027,63,-13.38,7.36,0.00431,58,-1.39,5.58,0.37692,48,-7.65,-6.25,0.00541,68,-24.08,-4.93,0.0,43,-0.58,-7.06,0.27564,64,-9.29,-9.61,0.01681,80,-14.27,-14.58,0.0006,7,28,-11.11,-6.16,0.02085,63,-7.28,9.33,0.08014,79,-13.15,12.45,0.00173,58,4.38,8.34,0.28371,43,5.54,-8.94,0.36244,64,-2.89,-9.93,0.20567,80,-8.08,-12.92,0.04542,1,43,0.28,-0.09,1.0,5,47,-1.91,-11.17,0.00653,43,7.82,3.28,0.40801,64,-3.66,2.48,0.17921,44,1.08,-4.83,0.40346,65,-10.24,-7.86,0.00277,4,43,15.69,3.51,0.133,64,3.9,4.62,0.33559,44,8.95,-4.94,0.47913,65,-2.63,-5.88,0.05225,5,64,9.4,4.06,0.1262,80,-0.69,4.16,0.42233,44,14.05,-7.05,0.03957,65,2.85,-6.56,0.33523,81,-5.53,-8.98,0.07664,3,80,5.55,4.62,0.648,65,8.89,-8.18,0.15115,81,0.68,-8.31,0.20084,5,28,2.44,-10.72,0.02743,48,2.13,-7.0,0.29251,47,-3.46,-0.28,0.41437,68,-14.99,-1.21,4e-05,43,-3.13,2.42,0.26561,7,47,4.7,-4.47,0.44694,68,-6.57,-4.88,0.04465,43,1.56,10.3,0.00547,44,-4.87,2.46,0.24971,45,-8.34,-0.81,0.02176,66,-19.44,-9.14,0.0,46,-6.42,-0.54,0.23144,1,46,1.61,-1.28,1.0,5,58,-6.86,36.96,0.0,45,8.75,4.04,0.25041,66,-5.6,2.01,0.02649,46,10.97,-4.2,0.65157,67,-1.83,-5.2,0.0715,5,58,-0.64,43.85,0.0,45,17.87,2.31,0.14332,66,3.46,3.98,0.68095,67,7.11,-7.65,0.14701,83,-2.72,-8.7,0.0287,5,58,4.5,48.84,0.0,66,10.56,5.02,0.43212,82,-1.89,4.62,0.42833,67,13.89,-10.01,0.01567,83,4.44,-8.97,0.12386,3,47,12.99,-6.58,0.16817,68,1.82,-6.46,0.50745,46,1.1,3.5,0.32437,4,58,-19.86,33.1,0.0,68,9.05,-5.82,0.5687,46,6.33,8.54,0.34322,67,-11.12,4.68,0.08807],"hull":82,"edges":[0,2,2,4,4,6,6,8,8,10,10,12,12,14,14,16,16,18,18,20,20,22,22,24,24,26,26,28,28,30,30,32,32,34,34,36,36,38,38,40,40,42,42,44,44,46,46,48,48,50,50,52,52,54,54,56,56,58,58,60,60,62,62,64,64,66,66,68,68,70,70,72,72,74,74,76,76,78,78,80,80,82,82,84,84,86,86,88,88,90,90,92,92,94,94,96,96,98,98,100,100,102,102,104,104,106,106,108,108,110,110,112,112,114,114,116,116,118,118,120,120,122,122,124,0,124,126,128,128,130,130,132,132,14,126,134,134,136,136,34,126,138,138,140,140,142,142,144,144,146,146,50,126,148,148,150,150,152,152,154,154,156,156,158,158,74,150,160,160,162,162,98],"width":63.0,"height":84.0}},"a_youdabi":{"a_youdabi_jienuosi4XT":{"type":"region","x":25.14,"y":3.13,"rotation":106.75,"width":50.0,"height":74.0}},"a_youxiaobi":{"a_youxiaobi_jienuosi4XT":{"type":"region","x":20.46,"y":1.57,"rotation":101.8,"width":31.0,"height":61.0}},"a_youshou":{"a_youshou_jienuosi4XT":{"type":"region","x":16.65,"y":3.79,"rotation":123.68,"width":49.0,"height":37.0}}}}],"animations":{"win":{"bones":{"guangqiu_jienuosi4XT":{"rotate":[{"time":0.0,"angle":0.0},{"time":-36.17188,"angle":-7.5813},{"time":9.12692,"angle":21.4954},{"time":20.68374,"angle":-10.3431},{"time":0.3333,"angle":0.0},{"time":0.0,"angle":0.8}]}}},"die":{"bones":{"a_cheek":{"rotate":[{"time":0.0,"angle":23.92},{"time":0.0666,"angle":-4.68},{"time":0.1333,"angle":-2.19},{"time":0.2,"angle":19.95},{"time":0.2666,"angle":27.39},{"time":0.3666,"angle":13.0},{"time":0.4666,"angle":14.51}]},"a_zuoshou":{"rotate":[{"time":0.0,"angle":-42.13},{"time":0.0666,"angle":-20.85,"curve":"stepped"},{"time":0.1333,"angle":-20.85},{"time":0.2,"angle":-45.38},{"time":0.2666,"angle":-69.09},{"time":0.3666,"angle":-20.85,"curve":"stepped"},{"time":0.4666,"angle":-20.85}]},"a_zuojiao":{"rotate":[{"time":0.0,"angle":182.11,"curve":"stepped"},{"time":0.0666,"angle":182.11},{"time":0.1333,"angle":131.04},{"time":0.2,"angle":89.63},{"time":0.2666,"angle":71.16},{"time":0.3666,"angle":72.76},{"time":0.4666,"angle":75.34}]},"bone42":{"rotate":[{"time":0.0,"angle":-0.69}]},"a_youdabi":{"rotate":[{"time":0.0,"angle":-1.57,"curve":"stepped"},{"time":0.0666,"angle":-1.57},{"time":0.1333,"angle":18.15},{"time":0.2,"angle":5.56},{"time":0.2666,"angle":1.28},{"time":0.3666,"angle":1.75},{"time":0.4666,"angle":-0.03}]},"a_youshou":{"rotate":[{"time":0.0,"angle":22.52,"curve":"stepped"},{"time":0.2666,"angle":22.52},{"time":0.3666,"angle":30.82},{"time":0.4666,"angle":29.04}]},"a_youxiaotui":{"rotate":[{"time":0.0,"angle":-6.0,"curve":"stepped"},{"time":0.0666,"angle":-6.0},{"time":0.1333,"angle":-18.28},{"time":0.2,"angle":-13.48},{"time":0.2666,"angle":-5.51},{"time":0.3666,"angle":-8.13},{"time":0.4666,"angle":-11.2}]},"a_youdatui":{"rotate":[{"time":0.0,"angle":8.22,"curve":"stepped"},{"time":0.0666,"angle":8.22},{"time":0.1333,"angle":-4.05},{"time":0.2,"angle":0.75},{"time":0.2666,"angle":8.71,"curve":"stepped"},{"time":0.4666,"angle":8.71}]},"Penhuo2":{"rotate":[{"time":0.0,"angle":11.28}]},"bone23":{"rotate":[{"time":0.0,"angle":0.72}]},"bone25":{"rotate":[{"time":0.0,"angle":-0.33}]},"a_zuodatui":{"rotate":[{"time":0.0,"angle":11.45,"curve":"stepped"},{"time":0.1333,"angle":11.45},{"time":0.2,"angle":6.71,"curve":"stepped"},{"time":0.2666,"angle":6.71},{"time":0.3666,"angle":9.52},{"time":0.4666,"angle":6.71}]},"a_youxiaobi":{"rotate":[{"time":0.0,"angle":4.06},{"time":0.0666,"angle":27.81},{"time":0.1333,"angle":11.72},{"time":0.2,"angle":-0.86},{"time":0.2666,"angle":-5.15},{"time":0.3666,"angle":27.9},{"time":0.4666,"angle":26.12}]},"bone29":{"rotate":[{"time":0.0,"angle":2.74}]},"bone47":{"rotate":[{"time":0.0,"angle":-3.37}]},"bone39":{"rotate":[{"time":0.0,"angle":-2.12}]},"bone9":{"rotate":[{"time":0.0,"angle":1.0}]},"a_shenti":{"rotate":[{"time":0.0666,"angle":0.0},{"time":0.1333,"angle":-15.8,"curve":"stepped"},{"time":0.2,"angle":-15.8},{"time":0.2666,"angle":-8.35,"curve":"stepped"},{"time":0.4666,"angle":-8.35}]},"a_youjiao":{"rotate":[{"time":0.0,"angle":160.5,"curve":"stepped"},{"time":0.0666,"angle":160.5},{"time":0.1333,"angle":92.44},{"time":0.2,"angle":81.55},{"time":0.2666,"angle":81.29},{"time":0.3666,"angle":85.61},{"time":0.4666,"angle":82.29}]},"ALL":{"rotate":[{"time":0.0,"angle":148.85},{"time":0.0666,"angle":162.59},{"time":0.1333,"angle":112.59},{"time":0.2,"angle":99.56},{"time":0.2666,"angle":84.25},{"time":0.3666,"angle":98.73,"curve":"stepped"},{"time":0.4666,"angle":98.73}]},"a_zuodabi":{"rotate":[{"time":0.0,"angle":10.62},{"time":0.0666,"angle":28.1},{"time":0.1333,"angle":17.75},{"time":0.2,"angle":-29.44},{"time":0.2666,"angle":-32.51},{"time":0.3666,"angle":-29.44,"curve":"stepped"},{"time":0.4666,"angle":-29.44}]},"bone11":{"rotate":[{"time":0.0,"angle":-3.37}]},"a_zuoxiaobi":{"rotate":[{"time":0.0,"angle":-8.91},{"time":0.0666,"angle":8.55,"curve":"stepped"},{"time":0.1333,"angle":8.55},{"time":0.2,"angle":27.48},{"time":0.2666,"angle":11.98},{"time":0.3666,"angle":27.48,"curve":"stepped"},{"time":0.4666,"angle":27.48}]},"guangqiu_jienuosi4XT3":{"rotate":[{"time":0.0,"angle":6.84}]},"bone18":{"rotate":[{"time":0.0,"angle":-2.12}]},"bone45":{"rotate":[{"time":0.0,"angle":1.0}]},"bone12":{"rotate":[{"time":0.0,"angle":-2.12}]},"bone40":{"rotate":[{"time":0.0,"angle":0.72}]},"a_zuoxioatui":{"rotate":[{"time":0.0,"angle":30.7,"curve":"stepped"},{"time":0.0666,"angle":30.7},{"time":0.1333,"angle":-2.19},{"time":0.2,"angle":-6.92,"curve":"stepped"},{"time":0.2666,"angle":-6.92},{"time":0.3666,"angle":-26.69},{"time":0.4666,"angle":-21.69}]},"bone30":{"rotate":[{"time":0.0,"angle":1.0}]},"bone46":{"rotate":[{"time":0.0,"angle":-1.63}]},"guangqiu_jienuosi4XT":{"translate":[{"time":0.0,"x":2.28,"y":0.52}]},"bone7":{"rotate":[{"time":0.0,"angle":1.0}]},"guangqiu_jienuosi4XT4":{"rotate":[{"time":0.0,"angle":6.84}]},"bone10":{"rotate":[{"time":0.0,"angle":-1.63}]},"bone":{"rotate":[{"time":0.0,"angle":-0.67},{"time":0.0666,"angle":-33.8},{"time":0.1333,"angle":-21.28},{"time":0.2,"angle":10.14},{"time":0.2666,"angle":17.59},{"time":0.3666,"angle":-9.49},{"time":0.4666,"angle":-7.99}]},"bone16":{"rotate":[{"time":0.0,"angle":-2.12}]},"bone32":{"rotate":[{"time":0.0,"angle":-2.65}]},"bone6":{"rotate":[{"time":0.0,"angle":2.74}]},"bone36":{"rotate":[{"time":0.0,"angle":0.72}]},"guangqiu_jienuosi4XT2":{"translate":[{"time":0.0,"x":2.28,"y":0.52}]},"bone27":{"rotate":[{"time":0.0,"angle":1.86}]},"bone13":{"rotate":[{"time":0.0,"angle":0.72}]},"bone15":{"rotate":[{"time":0.0,"angle":-3.99}]},"bone26":{"rotate":[{"time":0.0,"angle":-2.54}]},"bone37":{"rotate":[{"time":0.0,"angle":2.59}]},"bone38":{"rotate":[{"time":0.0,"angle":-3.99}]},"bone22":{"rotate":[{"time":0.0,"angle":-2.12}]},"bone41":{"rotate":[{"time":0.0,"angle":-2.65}]},"bone20":{"rotate":[{"time":0.0,"angle":2.59}]},"bone34":{"rotate":[{"time":0.0,"angle":1.5}]},"bone31":{"rotate":[{"time":0.0,"angle":-1.63}]},"bone35":{"rotate":[{"time":0.0,"angle":-2.12}]},"bone28":{"rotate":[{"time":0.0,"angle":-9.89}]},"bone8":{"rotate":[{"time":0.0,"angle":-1.63}]},"bone21":{"rotate":[{"time":0.0,"angle":-3.99}]},"bone17":{"rotate":[{"time":0.0,"angle":0.72}]},"bone43":{"rotate":[{"time":0.0,"angle":1.5}]},"bone19":{"rotate":[{"time":0.0,"angle":0.72}]},"bone49":{"rotate":[{"time":0.0,"angle":-7.09}]},"bone33":{"rotate":[{"time":0.0,"angle":-0.69}]},"bone24":{"rotate":[{"time":0.0,"angle":-5.43}]},"bone14":{"rotate":[{"time":0.0,"angle":2.59}]},"global/yinying":{"translate":[{"time":0.0,"x":0.0,"y":0.0},{"time":0.0666,"x":-71.44,"y":0.0},{"time":0.1333,"x":-37.2,"y":0.0},{"time":0.2666,"x":-50.6,"y":0.0},{"time":0.3666,"x":-56.55,"y":0.0}]}}},"attackAction":{"bones":{"a_kua":{"rotate":[{"time":0.0,"angle":0.0},{"time":0.0333,"angle":5.58,"curve":"stepped"},{"time":0.1,"angle":5.58,"curve":"stepped"},{"time":0.1333,"angle":4.41,"curve":"stepped"},{"time":0.1666,"angle":4.41,"curve":"stepped"},{"time":0.2,"angle":5.58,"curve":"stepped"},{"time":0.2333,"angle":4.41,"curve":"stepped"},{"time":0.2666,"angle":7.43,"curve":"stepped"},{"time":0.5,"angle":7.43,"curve":"stepped"},{"time":0.5333,"angle":4.41,"curve":"stepped"},{"time":0.5666,"angle":4.41,"curve":"stepped"},{"time":0.6,"angle":5.58,"curve":"stepped"},{"time":1.1,"angle":5.58},{"time":1.2666,"angle":0.0}]},"a_shenti":{"rotate":[{"time":0.2666,"angle":0.0},{"time":0.3666,"angle":-4.8},{"time":0.5,"angle":0.0,"curve":"stepped"},{"time":1.2666,"angle":0.0}]},"a_cheek":{"rotate":[{"time":0.0,"angle":0.98},{"time":0.0333,"angle":31.37},{"time":0.1,"angle":32.44,"curve":"stepped"},{"time":0.1333,"angle":10.27,"curve":"stepped"},{"time":0.1666,"angle":10.27,"curve":"stepped"},{"time":0.2,"angle":22.38,"curve":"stepped"},{"time":0.2333,"angle":29.72,"curve":"stepped"},{"time":0.2666,"angle":16.23},{"time":0.3666,"angle":20.92},{"time":0.5,"angle":12.0,"curve":"stepped"},{"time":0.5333,"angle":29.72,"curve":"stepped"},{"time":0.5666,"angle":19.61,"curve":"stepped"},{"time":0.6,"angle":3.78,"curve":"stepped"},{"time":1.1,"angle":3.78},{"time":1.2666,"angle":0.98}]},"a_zuodabi":{"rotate":[{"time":0.0,"angle":-0.95},{"time":0.0333,"angle":30.65},{"time":0.1,"angle":17.29,"curve":"stepped"},{"time":0.1333,"angle":83.36,"curve":"stepped"},{"time":0.1666,"angle":90.6,"curve":"stepped"},{"time":0.2,"angle":7.19,"curve":"stepped"},{"time":0.2333,"angle":-49.24,"curve":"stepped"},{"time":0.2666,"angle":-32.21},{"time":0.3666,"angle":-12.01},{"time":0.5,"angle":-33.5,"curve":"stepped"},{"time":0.5333,"angle":-78.21,"curve":"stepped"},{"time":0.5666,"angle":66.96,"curve":"stepped"},{"time":0.6,"angle":56.2},{"time":0.7,"angle":50.46},{"time":0.9,"angle":47.14},{"time":1.1,"angle":47.88},{"time":1.2666,"angle":-0.95}]},"a_zuoxiaobi":{"rotate":[{"time":0.0,"angle":-2.07},{"time":0.0333,"angle":84.21},{"time":0.1,"angle":103.45,"curve":"stepped"},{"time":0.1333,"angle":-24.09,"curve":"stepped"},{"time":0.1666,"angle":-8.41,"curve":"stepped"},{"time":0.2,"angle":98.43,"curve":"stepped"},{"time":0.2333,"angle":87.29,"curve":"stepped"},{"time":0.2666,"angle":-111.71},{"time":0.3666,"angle":-94.14},{"time":0.5,"angle":-56.36,"curve":"stepped"},{"time":0.5333,"angle":-114.64,"curve":"stepped"},{"time":0.5666,"angle":19.54,"curve":"stepped"},{"time":0.6,"angle":-2.51},{"time":0.7,"angle":12.77},{"time":0.9,"angle":5.12},{"time":1.1,"angle":6.84},{"time":1.2666,"angle":-2.07}]},"a_zuoshou":{"rotate":[{"time":0.0,"angle":-0.92},{"time":0.0333,"angle":-35.4,"curve":"stepped"},{"time":0.1,"angle":-35.4,"curve":"stepped"},{"time":0.1333,"angle":-93.51,"curve":"stepped"},{"time":0.1666,"angle":-82.71,"curve":"stepped"},{"time":0.2,"angle":-35.4,"curve":"stepped"},{"time":0.2333,"angle":-35.4,"curve":"stepped"},{"time":0.2666,"angle":-97.23,"curve":"stepped"},{"time":0.3666,"angle":-97.23},{"time":0.5,"angle":-107.08,"curve":"stepped"},{"time":0.5333,"angle":-107.08,"curve":"stepped"},{"time":0.5666,"angle":20.78,"curve":"stepped"},{"time":0.6,"angle":15.32,"curve":"stepped"},{"time":0.7,"angle":15.32},{"time":0.9,"angle":22.96},{"time":1.1,"angle":21.25},{"time":1.2666,"angle":-0.92}]},"guangqiu_jienuosi4XT":{"translate":[{"time":0.0,"x":2.28,"y":0.52},{"time":0.0333,"x":0.0,"y":0.0,"curve":"stepped"},{"time":1.1,"x":0.0,"y":0.0},{"time":1.2,"x":2.28,"y":0.52,"curve":"stepped"},{"time":1.2666,"x":2.28,"y":0.52}]},"guangqiu_jienuosi4XT2":{"translate":[{"time":0.0,"x":2.28,"y":0.52},{"time":0.0333,"x":0.0,"y":0.0,"curve":"stepped"},{"time":1.1,"x":0.0,"y":0.0},{"time":1.2,"x":2.28,"y":0.52,"curve":"stepped"},{"time":1.2666,"x":2.28,"y":0.52}]},"a_zuotuijin2":{"rotate":[{"time":0.0,"angle":2.4},{"time":0.0333,"angle":0.0,"curve":"stepped"},{"time":1.1,"angle":0.0},{"time":1.1333,"angle":2.4,"curve":"stepped"},{"time":1.2666,"angle":2.4}]},"a_youdabi":{"rotate":[{"time":0.0,"angle":2.4},{"time":0.0333,"angle":-26.17},{"time":0.1,"angle":-33.84,"curve":"stepped"},{"time":0.1333,"angle":-130.79,"curve":"stepped"},{"time":0.1666,"angle":-137.29,"curve":"stepped"},{"time":0.2,"angle":-32.0,"curve":"stepped"},{"time":0.2333,"angle":-224.67,"curve":"stepped"},{"time":0.2666,"angle":54.76},{"time":0.3666,"angle":33.83},{"time":0.5,"angle":30.76,"curve":"stepped"},{"time":0.5333,"angle":73.45,"curve":"stepped"},{"time":0.5666,"angle":-5.25,"curve":"stepped"},{"time":0.6,"angle":-1.3},{"time":0.7,"angle":-11.98},{"time":0.9,"angle":-21.58},{"time":1.1,"angle":-19.43},{"time":1.2666,"angle":2.4}]},"a_youxiaobi":{"rotate":[{"time":0.0,"angle":0.89},{"time":0.0333,"angle":12.92},{"time":0.1,"angle":5.25,"curve":"stepped"},{"time":0.1333,"angle":83.82,"curve":"stepped"},{"time":0.1666,"angle":62.6,"curve":"stepped"},{"time":0.2,"angle":-161.19,"curve":"stepped"},{"time":0.2333,"angle":-12.08,"curve":"stepped"},{"time":0.2666,"angle":-108.79},{"time":0.3666,"angle":-106.82},{"time":0.5,"angle":-97.3,"curve":"stepped"},{"time":0.5333,"angle":59.72,"curve":"stepped"},{"time":0.5666,"angle":94.51,"curve":"stepped"},{"time":0.6,"angle":61.34},{"time":0.7,"angle":34.29},{"time":0.9,"angle":36.86},{"time":1.1,"angle":36.28},{"time":1.2666,"angle":0.89}]},"a_youshou":{"rotate":[{"time":0.0,"angle":-1.39},{"time":0.0333,"angle":-19.83},{"time":0.1,"angle":-8.87,"curve":"stepped"},{"time":0.1333,"angle":50.6,"curve":"stepped"},{"time":0.1666,"angle":61.46,"curve":"stepped"},{"time":0.2,"angle":0.53,"curve":"stepped"},{"time":0.2333,"angle":23.85,"curve":"stepped"},{"time":0.2666,"angle":14.53,"curve":"stepped"},{"time":0.5,"angle":14.53,"curve":"stepped"},{"time":0.5333,"angle":36.86,"curve":"stepped"},{"time":0.5666,"angle":36.86,"curve":"stepped"},{"time":0.6,"angle":62.19},{"time":0.7,"angle":51.51},{"time":0.9,"angle":54.07},{"time":1.1,"angle":53.5},{"time":1.2666,"angle":-1.39}]},"guangqiu_jienuosi4XT3":{"rotate":[{"time":0.0,"angle":6.84},{"time":0.0333,"angle":0.0,"curve":"stepped"},{"time":1.1,"angle":0.0},{"time":1.2,"angle":6.84,"curve":"stepped"},{"time":1.2666,"angle":6.84}]},"guangqiu_jienuosi4XT4":{"rotate":[{"time":0.0,"angle":6.84},{"time":0.0333,"angle":0.0,"curve":"stepped"},{"time":1.1,"angle":0.0},{"time":1.2,"angle":6.84,"curve":"stepped"},{"time":1.2666,"angle":6.84}]},"a_youtuijin22":{"rotate":[{"time":0.0,"angle":-1.59},{"time":0.0333,"angle":0.0,"curve":"stepped"},{"time":1.1,"angle":0.0},{"time":1.2666,"angle":-1.59}]},"bone4":{"translate":[{"time":1.1,"x":0.0,"y":0.0},{"time":1.1333,"x":-10.14,"y":15.07},{"time":1.2666,"x":0.0,"y":0.0}]},"a_youdatui":{"rotate":[{"time":0.0,"angle":0.0},{"time":0.0333,"angle":17.31,"curve":"stepped"},{"time":0.1,"angle":17.31,"curve":"stepped"},{"time":0.1333,"angle":-10.32,"curve":"stepped"},{"time":0.1666,"angle":-13.44,"curve":"stepped"},{"time":0.2,"angle":-0.72,"curve":"stepped"},{"time":0.2333,"angle":9.18,"curve":"stepped"},{"time":0.2666,"angle":-8.59},{"time":0.3666,"angle":-13.4},{"time":0.5,"angle":-8.59,"curve":"stepped"},{"time":0.5333,"angle":10.56,"curve":"stepped"},{"time":0.5666,"angle":6.02,"curve":"stepped"},{"time":0.6,"angle":-4.99},{"time":0.7,"angle":-7.62},{"time":0.9,"angle":-4.99},{"time":1.1,"angle":-5.58},{"time":1.2666,"angle":0.0}]},"a_youxiaotui":{"rotate":[{"time":0.0,"angle":0.0},{"time":0.0333,"angle":-7.82,"curve":"stepped"},{"time":0.1,"angle":-7.82,"curve":"stepped"},{"time":0.1333,"angle":0.0,"curve":"stepped"},{"time":0.1666,"angle":-3.12,"curve":"stepped"},{"time":0.2,"angle":-11.32,"curve":"stepped"},{"time":0.2333,"angle":-35.49,"curve":"stepped"},{"time":0.2666,"angle":-35.09},{"time":0.3666,"angle":-38.23},{"time":0.5,"angle":-35.09,"curve":"stepped"},{"time":0.5333,"angle":-34.11,"curve":"stepped"},{"time":0.5666,"angle":-38.65,"curve":"stepped"},{"time":0.6,"angle":-11.32},{"time":0.7,"angle":-9.09},{"time":0.9,"angle":-11.32},{"time":1.1,"angle":-10.82},{"time":1.2666,"angle":0.0}]},"a_youjiao":{"rotate":[{"time":0.0,"angle":-0.8},{"time":0.0333,"angle":-43.8,"curve":"stepped"},{"time":0.1,"angle":-43.8,"curve":"stepped"},{"time":0.1333,"angle":-59.55,"curve":"stepped"},{"time":0.1666,"angle":-59.55,"curve":"stepped"},{"time":0.2,"angle":-9.98,"curve":"stepped"},{"time":0.2333,"angle":-6.88,"curve":"stepped"},{"time":0.2666,"angle":-9.98},{"time":0.3666,"angle":-19.46},{"time":0.5,"angle":-9.98,"curve":"stepped"},{"time":0.5333,"angle":-6.88,"curve":"stepped"},{"time":0.5666,"angle":-6.88,"curve":"stepped"},{"time":0.6,"angle":-9.98,"curve":"stepped"},{"time":1.1,"angle":-9.98},{"time":1.2666,"angle":-0.8}]},"a_zuodatui":{"rotate":[{"time":0.0,"angle":0.0},{"time":0.0333,"angle":97.36},{"time":0.1,"angle":111.58,"curve":"stepped"},{"time":0.1333,"angle":52.17,"curve":"stepped"},{"time":0.1666,"angle":65.11,"curve":"stepped"},{"time":0.2,"angle":80.03,"curve":"stepped"},{"time":0.2333,"angle":91.26,"curve":"stepped"},{"time":0.2666,"angle":70.98},{"time":0.3666,"angle":59.84},{"time":0.5,"angle":70.98,"curve":"stepped"},{"time":0.5333,"angle":91.26,"curve":"stepped"},{"time":0.5666,"angle":56.72,"curve":"stepped"},{"time":0.6,"angle":38.93},{"time":0.7,"angle":22.6},{"time":0.9,"angle":38.93},{"time":1.1,"angle":35.27},{"time":1.2666,"angle":0.0}]},"a_zuoxioatui":{"rotate":[{"time":0.0,"angle":0.0},{"time":0.0333,"angle":-85.75,"curve":"stepped"},{"time":0.1,"angle":-85.75,"curve":"stepped"},{"time":0.1333,"angle":-22.32,"curve":"stepped"},{"time":0.1666,"angle":-48.48,"curve":"stepped"},{"time":0.2,"angle":-48.02,"curve":"stepped"},{"time":0.2333,"angle":-43.65,"curve":"stepped"},{"time":0.5333,"angle":-43.65,"curve":"stepped"},{"time":0.5666,"angle":-8.68,"curve":"stepped"},{"time":0.6,"angle":1.52},{"time":0.7,"angle":22.58},{"time":0.9,"angle":1.52},{"time":1.1,"angle":6.24},{"time":1.2666,"angle":0.0}]},"a_zuojiao":{"rotate":[{"time":0.0,"angle":0.0},{"time":0.0333,"angle":-8.7,"curve":"stepped"},{"time":0.1,"angle":-8.7,"curve":"stepped"},{"time":0.1333,"angle":14.71,"curve":"stepped"},{"time":0.1666,"angle":-11.43,"curve":"stepped"},{"time":0.2,"angle":73.7,"curve":"stepped"},{"time":0.2333,"angle":67.6,"curve":"stepped"},{"time":0.2666,"angle":71.47,"curve":"stepped"},{"time":0.5,"angle":71.47,"curve":"stepped"},{"time":0.5333,"angle":67.6,"curve":"stepped"},{"time":0.5666,"angle":77.4,"curve":"stepped"},{"time":0.6,"angle":73.7,"curve":"stepped"},{"time":1.1,"angle":73.7},{"time":1.1333,"angle":16.48},{"time":1.2666,"angle":0.0}]},"ALL":{"rotate":[{"time":0.0,"angle":0.0},{"time":0.0333,"angle":-40.88},{"time":0.1,"angle":-53.6,"curve":"stepped"},{"time":0.1333,"angle":-29.22,"curve":"stepped"},{"time":0.1666,"angle":-18.54,"curve":"stepped"},{"time":0.2,"angle":-26.44,"curve":"stepped"},{"time":0.2333,"angle":-29.22,"curve":"stepped"},{"time":0.2666,"angle":-15.62},{"time":0.3666,"angle":-9.76},{"time":0.5,"angle":-15.62,"curve":"stepped"},{"time":0.5333,"angle":-29.22,"curve":"stepped"},{"time":0.5666,"angle":-14.61,"curve":"stepped"},{"time":0.6,"angle":-3.38},{"time":0.7,"angle":3.25},{"time":0.9,"angle":-3.38},{"time":1.1,"angle":-1.89},{"time":1.2666,"angle":0.0}]},"bone49":{"rotate":[{"time":0.0,"angle":-7.09,"curve":"stepped"},{"time":0.0333,"angle":-7.09},{"time":0.1,"angle":-109.93,"curve":"stepped"},{"time":1.1,"angle":-109.93},{"time":1.2,"angle":-7.09,"curve":"stepped"},{"time":1.2666,"angle":-7.09}]},"bone48":{"rotate":[{"time":0.0333,"angle":0.0},{"time":0.1,"angle":-41.7,"curve":"stepped"},{"time":0.1333,"angle":-112.5,"curve":"stepped"},{"time":1.1,"angle":-112.5},{"time":1.2,"angle":0.0,"curve":"stepped"},{"time":1.2666,"angle":0.0}]},"Penhuo2":{"translate":[{"time":0.0,"x":0.0,"y":0.0},{"time":0.0333,"x":-1.78,"y":3.35},{"time":0.1,"x":0.0,"y":0.0,"curve":"stepped"},{"time":1.1,"x":0.0,"y":0.0},{"time":1.2,"x":-1.78,"y":3.35},{"time":1.2666,"x":0.0,"y":0.0}]},"bone47":{"rotate":[{"time":0.0,"angle":-3.37},{"time":0.0333,"angle":0.0,"curve":"stepped"},{"time":1.1,"angle":0.0},{"time":1.2666,"angle":-3.37}]},"bone46":{"rotate":[{"time":0.0,"angle":-1.63},{"time":0.0333,"angle":0.0,"curve":"stepped"},{"time":1.1,"angle":0.0},{"time":1.2666,"angle":-1.63}]},"bone45":{"rotate":[{"time":0.0,"angle":1.0},{"time":0.0333,"angle":0.0,"curve":"stepped"},{"time":1.1,"angle":0.0},{"time":1.2666,"angle":1.0}]},"bone43":{"rotate":[{"time":0.0,"angle":1.5},{"time":0.0333,"angle":0.0,"curve":"stepped"},{"time":1.1,"angle":0.0},{"time":1.2666,"angle":1.5}]},"bone42":{"rotate":[{"time":0.0,"angle":-0.69},{"time":0.0333,"angle":0.0,"curve":"stepped"},{"time":1.1,"angle":0.0},{"time":1.2666,"angle":-0.69}]},"bone41":{"rotate":[{"time":0.0,"angle":-2.65},{"time":0.0333,"angle":0.0,"curve":"stepped"},{"time":1.1,"angle":0.0},{"time":1.2666,"angle":-2.65}]},"bone40":{"rotate":[{"time":0.0,"angle":0.72},{"time":0.0333,"angle":0.0,"curve":"stepped"},{"time":1.1,"angle":0.0},{"time":1.2666,"angle":0.72}]},"bone39":{"rotate":[{"time":0.0,"angle":-2.12},{"time":0.0333,"angle":0.0,"curve":"stepped"},{"time":1.1,"angle":0.0},{"time":1.2666,"angle":-2.12}]},"bone38":{"rotate":[{"time":0.0,"angle":-3.99},{"time":0.0333,"angle":0.0,"curve":"stepped"},{"time":1.1,"angle":0.0},{"time":1.2666,"angle":-3.99}]},"bone37":{"rotate":[{"time":0.0,"angle":2.59},{"time":0.0333,"angle":0.0,"curve":"stepped"},{"time":1.1,"angle":0.0},{"time":1.2666,"angle":2.59}]},"bone36":{"rotate":[{"time":0.0,"angle":0.72},{"time":0.0333,"angle":0.0,"curve":"stepped"},{"time":1.1,"angle":0.0},{"time":1.2666,"angle":0.72}]},"bone35":{"rotate":[{"time":0.0,"angle":-2.12},{"time":0.0333,"angle":0.0,"curve":"stepped"},{"time":1.1,"angle":0.0},{"time":1.2666,"angle":-2.12}]},"bone34":{"rotate":[{"time":0.0,"angle":1.5},{"time":0.0333,"angle":0.0,"curve":"stepped"},{"time":1.1,"angle":0.0},{"time":1.2666,"angle":1.5}]},"bone33":{"rotate":[{"time":0.0,"angle":-0.69},{"time":0.0333,"angle":0.0,"curve":"stepped"},{"time":1.1,"angle":0.0},{"time":1.2666,"angle":-0.69}]},"bone32":{"rotate":[{"time":0.0,"angle":-2.65},{"time":0.0333,"angle":0.0,"curve":"stepped"},{"time":1.1,"angle":0.0},{"time":1.2666,"angle":-2.65}]},"bone31":{"rotate":[{"time":0.0,"angle":-1.63},{"time":0.0333,"angle":0.0,"curve":"stepped"},{"time":1.1,"angle":0.0},{"time":1.2666,"angle":-1.63}]},"bone30":{"rotate":[{"time":0.0,"angle":1.0},{"time":0.0333,"angle":0.0,"curve":"stepped"},{"time":1.1,"angle":0.0},{"time":1.2666,"angle":1.0}]},"bone29":{"rotate":[{"time":0.0,"angle":2.74},{"time":0.0333,"angle":0.0,"curve":"stepped"},{"time":1.1,"angle":0.0},{"time":1.2666,"angle":2.74}]},"bone28":{"rotate":[{"time":0.0,"angle":-9.89},{"time":0.0333,"angle":0.0,"curve":"stepped"},{"time":1.1,"angle":0.0},{"time":1.2666,"angle":-9.89}]},"bone27":{"rotate":[{"time":0.0,"angle":1.86},{"time":0.0333,"angle":0.0,"curve":"stepped"},{"time":1.1,"angle":0.0},{"time":1.2666,"angle":1.86}]},"bone26":{"rotate":[{"time":0.0,"angle":-2.54},{"time":0.0333,"angle":0.0,"curve":"stepped"},{"time":1.1,"angle":0.0},{"time":1.2666,"angle":-2.54}]},"bone25":{"rotate":[{"time":0.0,"angle":-0.33},{"time":0.0333,"angle":0.0,"curve":"stepped"},{"time":1.1,"angle":0.0},{"time":1.2666,"angle":-0.33}]},"bone24":{"rotate":[{"time":0.0,"angle":-5.43},{"time":0.0333,"angle":0.0,"curve":"stepped"},{"time":1.1,"angle":0.0},{"time":1.2666,"angle":-5.43}]},"bone23":{"rotate":[{"time":0.0,"angle":0.72},{"time":0.0333,"angle":0.0,"curve":"stepped"},{"time":1.1,"angle":0.0},{"time":1.2666,"angle":0.72}]},"bone22":{"rotate":[{"time":0.0,"angle":-2.12},{"time":0.0333,"angle":0.0,"curve":"stepped"},{"time":1.1,"angle":0.0},{"time":1.2666,"angle":-2.12}]},"bone21":{"rotate":[{"time":0.0,"angle":-3.99},{"time":0.0333,"angle":0.0,"curve":"stepped"},{"time":1.1,"angle":0.0},{"time":1.2666,"angle":-3.99}]},"bone20":{"rotate":[{"time":0.0,"angle":2.59},{"time":0.0333,"angle":0.0,"curve":"stepped"},{"time":1.1,"angle":0.0},{"time":1.2666,"angle":2.59}]},"bone19":{"rotate":[{"time":0.0,"angle":0.72},{"time":0.0333,"angle":0.0,"curve":"stepped"},{"time":1.1,"angle":0.0},{"time":1.2666,"angle":0.72}]},"bone18":{"rotate":[{"time":0.0,"angle":-2.12},{"time":0.0333,"angle":0.0,"curve":"stepped"},{"time":1.1,"angle":0.0},{"time":1.2666,"angle":-2.12}]},"bone17":{"rotate":[{"time":0.0,"angle":0.72},{"time":0.0333,"angle":0.0,"curve":"stepped"},{"time":1.1,"angle":0.0},{"time":1.2666,"angle":0.72}]},"bone16":{"rotate":[{"time":0.0,"angle":-2.12},{"time":0.0333,"angle":0.0,"curve":"stepped"},{"time":1.1,"angle":0.0},{"time":1.2666,"angle":-2.12}]},"bone15":{"rotate":[{"time":0.0,"angle":-3.99},{"time":0.0333,"angle":0.0,"curve":"stepped"},{"time":1.1,"angle":0.0},{"time":1.2666,"angle":-3.99}]},"bone14":{"rotate":[{"time":0.0,"angle":2.59},{"time":0.0333,"angle":0.0,"curve":"stepped"},{"time":1.1,"angle":0.0},{"time":1.2666,"angle":2.59}]},"bone13":{"rotate":[{"time":0.0,"angle":0.72},{"time":0.0333,"angle":0.0,"curve":"stepped"},{"time":1.1,"angle":0.0},{"time":1.2666,"angle":0.72}]},"bone12":{"rotate":[{"time":0.0,"angle":-2.12},{"time":0.0333,"angle":0.0,"curve":"stepped"},{"time":1.1,"angle":0.0},{"time":1.2666,"angle":-2.12}]},"bone11":{"rotate":[{"time":0.0,"angle":-3.37},{"time":0.0333,"angle":0.0,"curve":"stepped"},{"time":1.1,"angle":0.0},{"time":1.2666,"angle":-3.37}]},"bone10":{"rotate":[{"time":0.0,"angle":-1.63},{"time":0.0333,"angle":0.0,"curve":"stepped"},{"time":1.1,"angle":0.0},{"time":1.2666,"angle":-1.63}]},"bone9":{"rotate":[{"time":0.0,"angle":1.0},{"time":0.0333,"angle":0.0,"curve":"stepped"},{"time":1.1,"angle":0.0},{"time":1.2666,"angle":1.0}]},"bone8":{"rotate":[{"time":0.0,"angle":-1.63},{"time":0.0333,"angle":0.0,"curve":"stepped"},{"time":1.1,"angle":0.0},{"time":1.2666,"angle":-1.63}]},"bone7":{"rotate":[{"time":0.0,"angle":1.0},{"time":0.0333,"angle":0.0,"curve":"stepped"},{"time":1.1,"angle":0.0},{"time":1.2666,"angle":1.0}]},"bone6":{"rotate":[{"time":0.0,"angle":2.74},{"time":0.0333,"angle":0.0,"curve":"stepped"},{"time":1.1,"angle":0.0},{"time":1.2666,"angle":2.74}]},"bone":{"rotate":[{"time":0.0,"angle":0.0},{"time":0.0333,"angle":-7.62},{"time":0.1,"angle":6.78,"curve":"stepped"},{"time":0.1333,"angle":0.0,"curve":"stepped"},{"time":0.1666,"angle":-15.49,"curve":"stepped"},{"time":0.2,"angle":-11.13,"curve":"stepped"},{"time":0.2333,"angle":0.0,"curve":"stepped"},{"time":0.2666,"angle":0.0},{"time":0.3666,"angle":-12.78},{"time":0.5,"angle":0.0,"curve":"stepped"},{"time":0.6,"angle":0.0},{"time":0.7,"angle":-7.21},{"time":0.9,"angle":4.29},{"time":1.1,"angle":1.71},{"time":1.2666,"angle":0.0}]},"global/yinying":{"translate":[{"time":0.0,"x":0.0,"y":0.0},{"time":0.0333,"x":-6.09,"y":0.0,"curve":"stepped"},{"time":0.1666,"x":-6.09,"y":0.0},{"time":0.2,"x":-9.9,"y":0.0,"curve":"stepped"},{"time":0.9,"x":-9.9,"y":0.0},{"time":1.2666,"x":0.0,"y":0.0}]}}},"skillAction":{"bones":{"guangqiu_jienuosi4XT":{"rotate":[{"time":0.0,"angle":0.0},{"time":-85.97247,"angle":-14.642},{"time":22.88134,"angle":43.5365},{"time":41.71374,"angle":-20.8445},{"time":0.0333,"angle":0.0},{"time":0.0,"angle":0.1},{"time":0.0,"angle":0.0},{"time":0.0,"angle":0.0,"curve":"stepped"},{"time":0.1666,"angle":0.0},{"time":0.0,"angle":0.2},{"time":0.0,"angle":0.0},{"time":0.0,"angle":0.0,"curve":"stepped"},{"time":0.2666,"angle":0.0},{"time":0.0,"angle":0.3666},{"time":0.0,"angle":0.0},{"time":0.0,"angle":0.0,"curve":"stepped"},{"time":0.5333,"angle":0.0}]}}},"guiwei":{"bones":{"bone49":{"rotate":[{"time":0.0,"angle":-7.09}]},"guangqiu_jienuosi4XT":{"translate":[{"time":0.0,"x":2.28,"y":0.52}]},"guangqiu_jienuosi4XT2":{"translate":[{"time":0.0,"x":2.28,"y":0.52}]},"guangqiu_jienuosi4XT3":{"rotate":[{"time":0.0,"angle":6.84}]},"guangqiu_jienuosi4XT4":{"rotate":[{"time":0.0,"angle":6.84}]}}}}}